[
    {
        "domain": 1,
        "topic": "GrabStart",
        "cmd": "GrabStart",
        "datetime": "2023/12/26_16:09:43:563000",
        "seqId4": 0
    },
    {
        "domain": 1,
        "topic": "GrabberStart",
        "cmd": "GrabberStart",
        "datetime": "2023/12/26_16:09:43:564000",
        "seqId8": 19
    },
    {
        "domain": 1,
        "topic": "GrabDoneEnd",
        "cmd": "GrabDoneEnd",
        "datetime": "2023/12/26_16:09:43:564000",
        "seqId1": 19
    },
    {
        "domain": 1,
        "topic": "GrabberCommandEnd",
        "cmd": "GrabberCommandEnd",
        "datetime": "2023/12/26_16:09:43:564000",
        "seqId5": 19
    },
    {
        "domain": 1,
        "topic": "GrabberCommandStart",
        "cmd": "GrabberCommandStart",
        "datetime": "2023/12/26_16:09:43:564000",
        "seqId6": 19
    },
    {
        "domain": 1,
        "topic": "GrabDoneStart",
        "cmd": "GrabDoneStart",
        "datetime": "2023/12/26_16:09:43:564000",
        "seqId2": 19
    },
    {
        "domain": 1,
        "topic": "GrabEnd",
        "cmd": "GrabEnd",
        "datetime": "2023/12/26_16:09:43:565000",
        "seqId3": 19
    },
    {
        "domain": 1,
        "topic": "GrabberEnd",
        "cmd": "GrabberEnd",
        "datetime": "2023/12/26_16:09:43:564000",
        "seqId7": 0
    },
    {
        "domain": 1,
        "topic": "GrabEnd",
        "cmd": "GrabEnd",
        "datetime": "2024/01/22_11:02:51:613000",
        "seqId": 19
    },
    {
        "domain": 1,
        "topic": "GrabStart",
        "cmd": "GrabStart",
        "datetime": "2024/01/22_11:02:51:610000",
        "seqId": 19
    },
    {
        "domain": 1,
        "topic": "GrabEnd",
        "cmd": "GrabEnd",
        "datetime": "2024/01/22_11:12:47:242000",
        "seqId": 19
    },
    {
        "domain": 1,
        "topic": "GrabStart",
        "cmd": "GrabStart",
        "datetime": "2024/01/22_11:12:47:240000",
        "seqId": 19
    }
]